<?xml version="1.0" encoding="UTF-8"?>
<LanguageData>

  <!-- EN: Need slave beds -->
  <NeedSlaveBeds>Потрібні ліжка для рабів</NeedSlaveBeds>
  <!-- EN: You have more slaves than you have slave beds. Someone will lack a place to sleep.\n\nEither make more beds, or change a colonist or prisoner bed to a slave bed.\n\nIf you have no resources, sleeping spots are free and can be placed instantly. -->
  <NeedSlaveBedsDesc>Недостатньо ліжок для рабів.\n\nПобудуйте більше ліжок або змініть призначення ліжка поселенця або бранця.\n\nЯкщо вам не вистачає ресурсів, побудуйте спальне місце — його спорудження миттєве і не потребує ресурсів.</NeedSlaveBedsDesc>

  <!-- EN: Slave unsuppressed -->
  <SlavesUnsuppressedLabel>Раба не пригнічено</SlavesUnsuppressedLabel>
  <!-- EN: {0_nameDef}'s suppression level is dangerously low. There is a good chance {0_pronoun} will rebel.\n\nMake sure there is a colonist assigned to warden work. Wardens will suppress slaves periodically to stop them from rebelling. -->
  <SlavesUnsuppressedDesc>{0_gender ? Раб: Рабиня} {0_nameDef} недостатньо {0_gender ? пригнічений : пригнічений}. Імовірно, що {0_pronoun} почне бунтувати.\n\nПереконайтеся, що серед поселенців є наглядач. Наглядачі періодично придушуватимуть рабів для запобігання повстанням.</SlavesUnsuppressedDesc>
  <!-- EN: Slave unattended -->
  <SlaveUnattendedLabel>Раб без нагляду</SlaveUnattendedLabel>
  <!-- EN: Slaves unattended -->
  <SlaveUnattendedMultipleLabel>Раби без нагляду</SlaveUnattendedMultipleLabel>
  <!-- EN: Some slaves are alone on a map with no able-bodied colonists around.\n\nSlaves left unattended like this are very likely to rebel within days or hours. -->
  <SlavesUnattendedDesc>За деякими рабами не слідкує жоден працездатний поселенець.\n\nРаби, залишені без нагляду, швидше за все піднімуть повстання найближчими днями або годинами.</SlavesUnattendedDesc>

  <!-- EN: {0} expected -->
  <RitualExpected>Очікується {0}</RitualExpected>
  <!-- EN: {0} opportunity -->
  <RitualOpportunity>Можливий ритуал: {0}</RitualOpportunity>
  <!-- EN: {0} expected for -->
  <RitualExpectedFor>{0} очікується для</RitualExpectedFor>
  <!-- EN: {0} days: Ritual opportunity ends. -->
  <RitualExpirationTime>Термін проведення ритуалу {0} днів.</RitualExpirationTime>
  <!-- EN: Expires in -->
  <RitualExpiresIn>Спливає за</RitualExpiresIn>
  <!-- EN: Completing {RITUAL_labelDef} will have these effects -->
  <RitualCompletionEffects>Проведення {RITUAL_labelDef} призведе до наступного</RitualCompletionEffects>
  <!-- EN: To begin the ritual, select a focus object and click the 'Begin {RITUAL_label}' command. The following are valid focus objects:\n{1} -->
  <RitualTargetsExplanation>Щоб розпочати ритуал, виберіть місце проведення та натисніть «Почати {RITUAL_label}». Відповідні місця проведення: \n{1} </RitualTargetsExplanation>
  <!-- EN: Following roles have a part in {RITUAL_label}:\n{1} -->
  <RitualRolesExplanation>Наступні ролі беруть участь у {RITUAL_label}:\n{1}</RitualRolesExplanation>
  <!-- EN: Click to jump to targets -->
  <RitualJumpToTargets>Натисніть, щоб перейти до цілей</RitualJumpToTargets>
  <!-- EN: Delaying {RITUAL_labelDef} will have following effects -->
  <RitualObligationDelayEffects>Затримка проведення {RITUAL_labelDef} має наступні наслідки</RitualObligationDelayEffects>
  <!-- EN: {0} days: {1} mood on all {2}s. -->
  <RitualObligationDelayEffectDesc>{0} днів: {1} настрої всім {2}</RitualObligationDelayEffectDesc>
  <!-- EN: In order to perform {0} you need to fill these roles -->
  <RitualUnfilledRoles> Для проведення {0} потрібні такі ролі</RitualUnfilledRoles>

  <!-- EN: {0} desired -->
  <IdeoBuildingMissing>Потрібно {0}</IdeoBuildingMissing>
  <!-- EN: {IDEO_name} requires that you have a {0} in your colony as long as {2} or higher.\n\n{0} is a variant of {BASEBUILDING_label}.{BUILDINGINFO}\n\nThis requirement is only active if {IDEO_name} is your faction's primary ideoligion, or there are {MINBELIEVERS} believers in your faction.{4}\n\nIf the requirement isn't met, these believers will become unhappy:\n{3} -->
  <IdeoBuildingMissingDesc>{IDEO_name} вимагає наявності {lookup: {0}; Case; 1} у вашому поселенні, якщо {2} або вище.\n\n{0} — це вид {lookup: {BASEBUILDING_label}; Case; 1}.{BUILDINGINFO}\n\nЦя вимога є актуальною, тільки якщо {IDEO_name} — основна ідеолігія вашої фракції, або у вас є хоча б {MINBELIEVERS} її послідовників.{4}.\n\nЯкщо вимоги не будуть дотримані, ці послідовники будуть незадоволені:\n{3}</IdeoBuildingMissingDesc>
  <!-- EN:  You can find it by opening the '{TABNAME}' tab of the architect menu. -->
  <IdeoBuildingArchitectTabDesc>Ви можете побудувати цю споруду, відкривши вкладку «{TABNAME}» у меню «Проекти».</IdeoBuildingArchitectTabDesc>
  <!-- EN:  It can be created at:\n{0}. -->
  <IdeoBuildingCanBeCraftedAt>Цю річ можна створити на наступних робочих місцях:\n{0}.</IdeoBuildingCanBeCraftedAt>
  <!-- EN: In order to dignify {0}, these room requirements must be met -->
  <IdeoBuildingRoomRequirementsDesc>Приміщення, гідне {0}, має відповідати таким вимогам</IdeoBuildingRoomRequirementsDesc>
  <!-- EN: expectations are -->
  <IdeoBuildingExpectations>очікування —</IdeoBuildingExpectations>

  <!-- EN: {0} disrespected -->
  <IdeoBuildingDisrespected>{0} зганьблено</IdeoBuildingDisrespected>
  <!-- EN: {0} requires that {1} be in a dignified room. These room requirements must be met:\n{2}\n\nIf the {1}'s room requirements are not met, these believers will become unhappy:\n{3} -->
  <IdeoBuildingDisrespectedDesc>Згідно з традиціями {0}, приміщення для {1} має відповідати таким вимогам:\n{2}\n\nЯкщо вимоги не будуть дотримані, ці послідовники засмутяться:\n{3}</IdeoBuildingDisrespectedDesc>

  <!-- EN: Raids arriving in {0} -->
  <QuestPartRaidsDelay>Рейди розпочнуться за {0}</QuestPartRaidsDelay>
  <!-- EN: Raids will start arriving in {0}.\n\nThe raiders will target the spacedrone and attempt to destroy it. Protect the spacedrone so your colonists can hack its computer and retrieve the data. -->
  <QuestPartRaidsDelayDesc>Нальоти розпочнуться за {0}.\n\nНальотчики намагатимуться знищити космічний дрон. Захищайте його, щоб ваші поселенці могли зламати бортовий комп'ютер та отримати дані.</QuestPartRaidsDelayDesc>

  <!-- EN: {0} role unfilled -->
  <IdeoRoleEmpty>Роль {0} не призначена</IdeoRoleEmpty>
  <!-- EN: {0} roles unfilled -->
  <IdeoRolesEmpty>Ролі {0} не призначені</IdeoRolesEmpty>
  <!-- EN: These roles are not filled:\n{0}\n\nYou can assign someone a role on their Social tab. You can also select a ritual spot or an altar and click 'Begin role change'. \n\nIf these roles remain empty, the following people will be unhappy -->
  <IdeoRolesEmptyDesc>Ролі не призначені:\n{0}\n\nВи можете призначити роль поселенцю у вкладці "Соціум". Ви також можете вибрати місце проведення ритуалу або вівтар і натиснути кнопку «Почати зміну ролі».</IdeoRolesEmptyDesc>

  <!-- EN: Security threats activated in {0} -->
  <AncientAltarThreatsWaking>Система безпеки активується за {0}</AncientAltarThreatsWaking>
  <!-- EN: Security threats will activate in {0}. They will attack any who may threaten the relic. -->
  <AncientAltarThreatsWakingDesc>Система безпеки активується за {0}. </AncientAltarThreatsWakingDesc>

  <!-- EN: Ritual opportunity soon -->
  <AlertRitualComing>Скоро можна провести ритуал</AlertRitualComing>
  <!-- EN: A ritual opportunity is coming soon for following rituals -->
  <AlertRitualComingDesc>Незабаром можна провести наступні ритуали</AlertRitualComingDesc>
  <!-- EN: Opportunities expire after {0} days, and reoccur on the same day each year. -->
  <AlertRitualComingExtra>Можливість проведення ритуалу спливає за {0_numCase ? день : дня : днів} і з'являється щорічно того ж дня.</AlertRitualComingExtra>
  <!-- EN: {0} on {1}, {2} left -->
  <AlertRitualComingEntry>{0} проводиться {1}, залишилося {2}</AlertRitualComingEntry>

  <!-- EN: Age reversal demanded -->
  <AlertAgeReversalDemandNear>Потрібно омолодження</AlertAgeReversalDemandNear>
  <!-- EN: Because of their beliefs, some of your colonists demand regular age reversal treatments in a biosculpter pod. If they don't get the treatments, they will be displeased.\n\nThe following people demand age reversal treatment -->
  <AlertAgeReversalDemandDesc>Переконання деяких ваших поселенців вимагають від них регулярно омолоджуватися в біоскульпторі. Якщо цього не робити, вони будуть незадоволені.\n\nПроцедура омолодження потрібна наступним поселенцям</AlertAgeReversalDemandDesc>
  <!-- EN: {PAWN} joined {FACTION} recently, and wants to begin age reversal treatments in {DURATION}. -->
  <AlertAgeReversalDemandDesc_Recruit>{PAWN} нещодавно {PAWN_gender ? приєднався : приєдналася} до фракції {FACTION} і вимагає омолодження в найближчі {DURATION}</AlertAgeReversalDemandDesc_Recruit>
  <!-- EN: {PAWN} wants their next treatment in {DURATION}. -->
  <AlertAgeReversalDemandDesc_Next>{PAWN} вимагає проведення омолодження у найближчі {DURATION}</AlertAgeReversalDemandDesc_Next>
  <!-- EN: {PAWN} wants their first treatment in {DURATION}. -->
  <AlertAgeReversalDemandDesc_Initial>{PAWN} вимагає проведення свого першого омолодження в найближчі {DURATION}</AlertAgeReversalDemandDesc_Initial>
  <!-- EN: {PAWN}'s treatment is overdue by {DURATION}. -->
  <AlertAgeReversalDemandDesc_Overdue>Омолодження {PAWN} прострочено на {DURATION}.</AlertAgeReversalDemandDesc_Overdue>

  <!-- EN: {PAWN_nameDef}'s belief in {IDEO_name} prevents {PAWN_objective} from eating the meat of {ANIMALS}. -->
  <AlertRoyalTitleNoVeneratedAnimalMeat>Віра {PAWN_nameDef} у {IDEO_name} забороняє вживати в їжу м'ясо цих тварин: {ANIMALS}.</AlertRoyalTitleNoVeneratedAnimalMeat>

  <!-- EN: Dryad caste not set -->
  <AlertGauranlenTreeWithoutDryadTypeLabel>Не вибрано касту дріад</AlertGauranlenTreeWithoutDryadTypeLabel>
  <!-- EN: One or more Gauranlen trees do not have their dryad caste set.\n\nSelect the tree and click the '{0}' button to set produced dryad caste. -->
  <AlertGauranlenTreeWithoutDryadTypeDesc>В одному або більше деревах Гауранлен не вибрано касти дріад. Виберіть дерево і натисніть «{0)», щоб обрати касту дріад, що вирощується.</AlertGauranlenTreeWithoutDryadTypeDesc>
  <!-- EN: Connector not assigned to plant cutting -->
  <AlertConnectedPawnNotAssignedToPlantCuttingLabel>Пов'язаного не призначено садівником</AlertConnectedPawnNotAssignedToPlantCuttingLabel>
  <!-- EN: You have Gauranlen trees which are set to be pruned, but their connectors are not assigned to plant cutting.\n\nYou should assign plant cutting work to the following people -->
  <AlertConnectedPawnNotAssignedToPlantCuttingDesc>Дерева Гауранлен очікують остригання, але їх пов'язані не призначені садівниками.\n\nВам слід призначити садівниками наступних поселенців</AlertConnectedPawnNotAssignedToPlantCuttingDesc>

  <!-- EN: Fuel node explodes in {0} -->
  <AlertFuelNodeIgniting>Паливний вузол вибухне за {0}</AlertFuelNodeIgniting>
  <!-- EN: A fuel node has ignited! It will melt down and explode very soon.\n\nGet away and be ready to fight or escape the fires. -->
  <AlertFuelNodeIgnitingDesc>Паливний вузол спалахнув! Незабаром він розплавиться і вибухне. Відійдіть подалі і будьте готові до гасіння пожежі. </AlertFuelNodeIgnitingDesc>

  <!-- EN: Insects arriving in {0} -->
  <AlertInfestationArriving>Комахи прибувають за {0}</AlertInfestationArriving>
  <!-- EN: Giant insects have sensed your activity and are burrowing up from underground to attack. Infestations are about to begin. -->
  <AlertInfestationArrivingDesc>Гігантські комахи відчули вашу присутність і пробираються до вас з-під землі, щоб напасти. Нашестя комах скоро почнеться.</AlertInfestationArrivingDesc>

  <!-- EN: {0_pawnsPlural} waking in {1} -->
  <AlertHostilesWakingUp>{0_pawnsPlural} прокинеться за {1}</AlertHostilesWakingUp>
  <!-- EN: One or more {0_pawnsPlural} are waking up.\n\nThey will attack if they find you. -->
  <AlertHostilesWakingUpDesc>Один або більше {0_pawnsPlural} прокидаються.\n\nВони нападуть, якщо вас знайдуть.</AlertHostilesWakingUpDesc>

  <!-- EN: Cryptosleep caskets opening in {0} -->
  <AlertCasketOpening>Саркофаги криптосну відкриються за {0}</AlertCasketOpening>
  <!-- EN: Cryptosleep caskets containing unknown threats are opening soon. -->
  <AlertCasketOpeningDesc>Невідома загроза, що дрімає в саркофагах криптосна, незабаром прокинеться.</AlertCasketOpeningDesc>

  <!-- EN: Slave rebellion likely -->
  <AlertSlaveRebellionLikely>Можливе повстання рабів</AlertSlaveRebellionLikely>
  <!-- EN: There are {REBELLIOUSCOUNT} slaves that are likely to initiate a rebellion. -->
  <AlertSlaveRebellionLikelyRebelliousCount>У вас в поселенні є {REBELLIOUSCOUNT} рабів, які можуть розпочати повстання.</AlertSlaveRebellionLikelyRebelliousCount>
  <!-- EN: A slave rebellion is expected to happen roughly once every {COMBINEDTIME}. Note that each slave's rebellion chance is independent, so if any one of them rebels they can take others with them.\n\n{REBEL_labelShort} is the most rebellious slave and is expected to initiate a rebellion roughly once every {INDIVIDUALTIME}. The following factors are affecting how often they will rebel: -->
  <AlertSlaveRebellionLikelyMostRebellious>Повстання рабів очікуються приблизно раз у {COMBINEDTIME}. Зверніть увагу, що ймовірність підняти повстання розраховується індивідуально для кожного з рабів, і будь-який з них, хто підніме повстання, може повести за собою інших. приблизно раз на {INDIVIDUALTIME}. На це впливають такі фактори:</AlertSlaveRebellionLikelyMostRebellious>

</LanguageData>